Metadata-Version: 1.0
Name: prob-udacitybatu
Version: 0.1
Summary: Gaussian and Binomial distributions
Home-page: UNKNOWN
Author: Batuhan Panavur
Author-email: bpanavuraj@gmail.com
License: UNKNOWN
Platform: UNKNOWN
